{"mean":{"confidence_interval":{"confidence_level":0.95,"lower_bound":873818.0804753914,"upper_bound":876510.6482939388},"point_estimate":875028.5392807364,"standard_error":690.506140402459},"median":{"confidence_interval":{"confidence_level":0.95,"lower_bound":872572.08,"upper_bound":873524.7391304348},"point_estimate":872839.1390827517,"standard_error":187.6731995807924},"median_abs_dev":{"confidence_interval":{"confidence_level":0.95,"lower_bound":845.9317518229975,"upper_bound":2184.9272072423996},"point_estimate":1311.3776886119683,"standard_error":303.46053268265524},"slope":{"confidence_interval":{"confidence_level":0.95,"lower_bound":873280.5666260172,"upper_bound":875031.1942033664},"point_estimate":874074.8693763854,"standard_error":448.6566009390192},"std_dev":{"confidence_interval":{"confidence_level":0.95,"lower_bound":3405.504704407561,"upper_bound":9978.195150666017},"point_estimate":6943.020366046372,"standard_error":1705.4612390178809}}