{"mean":{"confidence_interval":{"confidence_level":0.95,"lower_bound":605773.5440745621,"upper_bound":612778.1370162242},"point_estimate":609019.181196503,"standard_error":1798.538905222759},"median":{"confidence_interval":{"confidence_level":0.95,"lower_bound":601224.0892857143,"upper_bound":603414.7871295372},"point_estimate":602170.9773809523,"standard_error":557.9270842296027},"median_abs_dev":{"confidence_interval":{"confidence_level":0.95,"lower_bound":1840.8002991373016,"upper_bound":4608.1885859678805},"point_estimate":3003.7464386345773,"standard_error":722.1013033202405},"slope":{"confidence_interval":{"confidence_level":0.95,"lower_bound":603107.2629016286,"upper_bound":607253.2747080264},"point_estimate":604995.1660573371,"standard_error":1065.9940349229169},"std_dev":{"confidence_interval":{"confidence_level":0.95,"lower_bound":11608.893477731284,"upper_bound":23387.379972091156},"point_estimate":18083.401433827254,"standard_error":3006.1465074593034}}