{"mean":{"confidence_interval":{"confidence_level":0.95,"lower_bound":946901.3953144519,"upper_bound":949929.805002784},"point_estimate":948283.5882936519,"standard_error":777.6554839746603},"median":{"confidence_interval":{"confidence_level":0.95,"lower_bound":945734.8400000001,"upper_bound":946285.25},"point_estimate":946116.8125,"standard_error":152.16878206573045},"median_abs_dev":{"confidence_interval":{"confidence_level":0.95,"lower_bound":968.7525765627779,"upper_bound":2801.5559160957237},"point_estimate":1645.1109164327695,"standard_error":443.2938224757713},"slope":{"confidence_interval":{"confidence_level":0.95,"lower_bound":946333.3211959577,"upper_bound":947579.8388280184},"point_estimate":946917.7280183242,"standard_error":317.98493759043293},"std_dev":{"confidence_interval":{"confidence_level":0.95,"lower_bound":4060.4636247196436,"upper_bound":10861.443889968052},"point_estimate":7792.93776338226,"standard_error":1740.3889978203315}}